genr/__init__.py
genr/dialog.py
genr/generate.py
genr/info.py
genr/main.py
genr/templates/gitignore/.gitignore
genr/templates/gitignore/README.md
genr/templates/license/LICENSE
genr/templates/license/README.md
genr/templates/pylint/README.md
genr/templates/pylint/pylint.yml
genr/templates/pylintrc/.pylintrc
genr/templates/pylintrc/README.md
genr/templates/pyproject/README.md
genr/templates/pyproject/pyproject.toml
genr/templates/python-publish/README.md
genr/templates/python-publish/python-publish.yml
genr-0.2.0.dist-info/licenses/LICENSE
genr-0.2.0.dist-info/METADATA
genr-0.2.0.dist-info/WHEEL
genr-0.2.0.dist-info/entry_points.txt
genr-0.2.0.dist-info/top_level.txt
genr-0.2.0.dist-info/RECORD
