Metadata-Version: 2.4
Name: genr
Version: 0.2.0
Summary: Generates default templates ready to use via a cli
Author-email: devs_des1re <arjunbrij8811@gmail.com>
Maintainer-email: devs_des1re <arjunbrij8811@gmail.com>
License-Expression: MIT
Project-URL: Homepage, https://github.com/devs-des1re/genr
Keywords: app,macOS,windows,linux,flatpak
Classifier: Development Status :: 4 - Beta
Classifier: Environment :: Console
Classifier: Intended Audience :: Developers
Classifier: Operating System :: OS Independent
Classifier: Programming Language :: Python :: 3
Classifier: Programming Language :: Python :: 3.10
Classifier: Programming Language :: Python :: 3.11
Classifier: Programming Language :: Python :: 3.12
Classifier: Programming Language :: Python :: 3.13
Classifier: Programming Language :: Python :: 3.14
Classifier: Programming Language :: Python :: 3 :: Only
Classifier: Topic :: Software Development
Classifier: Topic :: Utilities
Requires-Python: >=3.10
License-File: LICENSE
Requires-Dist: pip>=21.2
Requires-Dist: typer~=0.16
Dynamic: license-file
